rose_nielsen_sdk-0.1.5.dist-info/licenses/LICENSE
swaggerpetstore/__init__.py
swaggerpetstore/api_helper.py
swaggerpetstore/configuration.py
swaggerpetstore/swaggerpetstore_client.py
swaggerpetstore/controllers/__init__.py
swaggerpetstore/controllers/base_controller.py
swaggerpetstore/controllers/pet_controller.py
swaggerpetstore/controllers/store_controller.py
swaggerpetstore/controllers/user_controller.py
swaggerpetstore/exceptions/__init__.py
swaggerpetstore/exceptions/api_exception.py
swaggerpetstore/exceptions/o_auth_provider_exception.py
swaggerpetstore/http/__init__.py
swaggerpetstore/http/http_call_back.py
swaggerpetstore/http/http_method_enum.py
swaggerpetstore/http/http_request.py
swaggerpetstore/http/http_response.py
swaggerpetstore/http/proxy_settings.py
swaggerpetstore/http/auth/__init__.py
swaggerpetstore/http/auth/api_key.py
swaggerpetstore/http/auth/http_basic.py
swaggerpetstore/http/auth/petstore_auth.py
swaggerpetstore/models/__init__.py
swaggerpetstore/models/api_response.py
swaggerpetstore/models/category.py
swaggerpetstore/models/category_2.py
swaggerpetstore/models/content_type_enum.py
swaggerpetstore/models/o_auth_provider_error_enum.py
swaggerpetstore/models/o_auth_scope_petstore_auth_enum.py
swaggerpetstore/models/o_auth_token.py
swaggerpetstore/models/order.py
swaggerpetstore/models/pet.py
swaggerpetstore/models/pet_request.py
swaggerpetstore/models/status_1_enum.py
swaggerpetstore/models/status_2_enum.py
swaggerpetstore/models/status_enum.py
swaggerpetstore/models/store_order_request.py
swaggerpetstore/models/tag.py
swaggerpetstore/models/user.py
swaggerpetstore/models/user_request.py
swaggerpetstore/utilities/__init__.py
swaggerpetstore/utilities/file_wrapper.py
rose_nielsen_sdk-0.1.5.dist-info/METADATA
rose_nielsen_sdk-0.1.5.dist-info/WHEEL
rose_nielsen_sdk-0.1.5.dist-info/top_level.txt
rose_nielsen_sdk-0.1.5.dist-info/RECORD
