Metadata-Version: 2.4
Name: rose-nielsen-sdk
Version: 0.1.5
Summary: Eiusmod facilis quis
Author-email: Zahra Naseem <tukala@mailinator.com>
Project-URL: Documentation, https://documentation.com
Requires-Python: >=3.7
License-File: LICENSE
Requires-Dist: apimatic-core>=0.2.22,~=0.2.0
Requires-Dist: apimatic-core-interfaces>=0.1.5,~=0.1.0
Requires-Dist: apimatic-requests-client-adapter>=0.1.8,~=0.1.0
Requires-Dist: deprecation~=2.1
Provides-Extra: testutils
Requires-Dist: pytest>=7.2.2; extra == "testutils"
Dynamic: license-file
